AUTHORS
LICENSE
MANIFEST.in
README.rst
setup.cfg
setup.py
docs/Makefile
docs/conf.py
docs/index.rst
docs/make.bat
pypasswd/__init__.py
pypasswd/generator.py
pypasswd.egg-info/PKG-INFO
pypasswd.egg-info/SOURCES.txt
pypasswd.egg-info/dependency_links.txt
pypasswd.egg-info/entry_points.txt
pypasswd.egg-info/requires.txt
pypasswd.egg-info/top_level.txt
pypasswd.egg-info/zip-safe