Metadata-Version: 2.1
Name: pypasswd
Version: 1.0.0
Summary: a simple and secure password generation library
Home-page: https://pypasswd.zuh0.com
Author: Gabriel Duque
Author-email: gabriel@zuh0.com
License: MIT
Download-URL: https://github.com/zuh0/pypasswd/archive/v1.0.0.tar.gz
Project-URL: Documentation, https://pypasswd.zuh0.com
Project-URL: Source, https://github.com/zuh0/pypasswd
Project-URL: Tracker, https://github.com/zuh0/pypasswd/issues
Platform: UNKNOWN
Classifier: Development Status :: 4 - Beta
Classifier: Environment :: Console
Classifier: Intended Audience :: Developers
Classifier: Intended Audience :: System Administrators
Classifier: License :: OSI Approved :: MIT License
Classifier: Operating System :: OS Independent
Classifier: Programming Language :: Python
Classifier: Programming Language :: Python :: 3
Classifier: Programming Language :: Python :: 3 :: Only
Classifier: Programming Language :: Python :: 3.6
Classifier: Programming Language :: Python :: 3.7
Classifier: Programming Language :: Python :: 3.8
Classifier: Programming Language :: Python :: 3.9
Classifier: Topic :: Security
Classifier: Typing :: Typed
Requires-Python: >=3.6
Provides-Extra: doc
Provides-Extra: dev
